coinexpy/__init__.py
coinexpy/coinex.py
coinexpy/requestclient.py
coinexpy-0.2.dist-info/LICENSE
coinexpy-0.2.dist-info/LICENSE.txt
coinexpy-0.2.dist-info/METADATA
coinexpy-0.2.dist-info/WHEEL
coinexpy-0.2.dist-info/top_level.txt
coinexpy-0.2.dist-info/RECORD
