Metadata-Version: 2.1
Name: coinexpy
Version: 0.2
Summary: Python wrapper for Coinex APIs
Home-page: https://github.com/imanmousaei/coinexpy
Author: Iman Mousaei
Author-email: imanmousaei1379@gmail.com
License: MIT
Download-URL: https://github.com/imanmousaei/coinexpy/archive/refs/tags/v0.2-alpha.tar.gz
Keywords: coinex,api,wrapper,trade,crypto,bitcoin
Platform: UNKNOWN
Classifier: Development Status :: 3 - Alpha
Classifier: Intended Audience :: Developers
Classifier: Topic :: Software Development :: Build Tools
Classifier: License :: OSI Approved :: MIT License
Classifier: Programming Language :: Python :: 3
Classifier: Programming Language :: Python :: 3.4
Classifier: Programming Language :: Python :: 3.5
Classifier: Programming Language :: Python :: 3.6
Classifier: Programming Language :: Python :: 3.7
Classifier: Programming Language :: Python :: 3.8
License-File: LICENSE
License-File: LICENSE.txt
Requires-Dist: hashlib
Requires-Dist: json
Requires-Dist: urllib3
